setup.py
malyzm.egg-info/PKG-INFO
malyzm.egg-info/SOURCES.txt
malyzm.egg-info/dependency_links.txt
malyzm.egg-info/top_level.txt
pakiet_testowy/__init__.py
pakiet_testowy/dzialania.py