Metadata-Version: 2.1
Name: malyzm
Version: 1.0
Summary: Pakiet testowy
Home-page: http://sda.com
License: UNKNOWN
Platform: UNKNOWN
